sysnet_directory/__init__.py
sysnet_directory/factory.py
sysnet_directory-1.1.7.dist-info/LICENSE.md
sysnet_directory-1.1.7.dist-info/METADATA
sysnet_directory-1.1.7.dist-info/WHEEL
sysnet_directory-1.1.7.dist-info/top_level.txt
sysnet_directory-1.1.7.dist-info/RECORD
