Metadata-Version: 2.1
Name: sysnet-directory
Version: 1.1.7
Summary: Directory client library
Author-email: Data Developer <info@sysnet.cz>
License: # LICENCE PRO DOMÁCÍ POUŽITÍ (SYSNET Home Use License) v 1.0
Project-URL: Homepage, https://github.com/SYSNET-CZ/esmlouvy/tree/main/directory
Classifier: Development Status :: 5 - Production/Stable
Classifier: Programming Language :: Python :: 3
Classifier: License :: Free For Home Use
Classifier: Operating System :: OS Independent
Classifier: Topic :: System :: Systems Administration :: Authentication/Directory :: LDAP
Requires-Python: >=3.9
License-File: LICENSE.md
